rewiring/__init__.py
rewiring/disassortative_rewiring.py
rewiring-1.0.0.dev1.dist-info/DESCRIPTION.rst
rewiring-1.0.0.dev1.dist-info/METADATA
rewiring-1.0.0.dev1.dist-info/RECORD
rewiring-1.0.0.dev1.dist-info/WHEEL
rewiring-1.0.0.dev1.dist-info/metadata.json
rewiring-1.0.0.dev1.dist-info/top_level.txt
