Metadata-Version: 2.0
Name: rewiring
Version: 1.0.0.dev1
Summary: second_order_assortative_mixing_disassortative_rewiring
Home-page: UNKNOWN
Author: Yu, Xianglei
Author-email: UNKNOWN
License: UNKNOWN
Platform: UNKNOWN
